MANIFEST.in
README.rst
setup.py
angap/calculateRho.py
angap/computeCosAnalysis.py
angap/computeParameterTrends.py
angap/findMaxGapTime.py
angap/findPPDBothMethods.py
angap/plotAnalyticalSimulationError.py
angap/plotCosAnalysis.py
angap/plotParameterTrends.py
angap/plotParameterTrendsLines.py
angap/plotSingleParameterAnalysis.py
angap.egg-info/PKG-INFO
angap.egg-info/SOURCES.txt
angap.egg-info/dependency_links.txt
angap.egg-info/top_level.txt