Metadata-Version: 2.1
Name: angap
Version: 0.1
Summary: Geometric Approach for Analytical Approximations of Satellite Coverage Statistics
Author: Tim Hackett
License: MIT
Keywords: Analytical Coverage Approximations
Classifier: Development Status :: 3 - Alpha
Classifier: Intended Audience :: Developers
Classifier: Topic :: Software Development :: Build Tools
Classifier: License :: OSI Approved :: MIT License
Classifier: Programming Language :: Python :: 3.6
